tikorgzo/__init__.py
tikorgzo/__main__.py
tikorgzo/_version.py
tikorgzo/console.py
tikorgzo/constants.py
tikorgzo/exceptions.py
tikorgzo/generic.py
tikorgzo/py.typed
tikorgzo/utils.py
tikorgzo/cli/args_handler.py
tikorgzo/cli/args_validator.py
tikorgzo/cli/workflow.py
tikorgzo/config/__init__.py
tikorgzo/config/constants.py
tikorgzo/config/mapper.py
tikorgzo/config/model.py
tikorgzo/config/parser.py
tikorgzo/config/provider.py
tikorgzo/core/download_manager/__init__.py
tikorgzo/core/download_manager/downloader.py
tikorgzo/core/download_manager/queue.py
tikorgzo/core/extractors/base.py
tikorgzo/core/extractors/constants.py
tikorgzo/core/extractors/context_manager.py
tikorgzo/core/extractors/direct/extractor.py
tikorgzo/core/extractors/direct/helpers.py
tikorgzo/core/extractors/tikwm/browser.py
tikorgzo/core/extractors/tikwm/constants.py
tikorgzo/core/extractors/tikwm/extractor.py
tikorgzo/core/video/__init__.py
tikorgzo/core/video/model.py
tikorgzo/core/video/processor.py
tikorgzo-0.4.0.dist-info/licenses/LICENSE
tikorgzo-0.4.0.dist-info/METADATA
tikorgzo-0.4.0.dist-info/WHEEL
tikorgzo-0.4.0.dist-info/entry_points.txt
tikorgzo-0.4.0.dist-info/top_level.txt
tikorgzo-0.4.0.dist-info/RECORD
