Metadata-Version: 2.4
Name: Tikorgzo
Version: 0.4.0
Summary: A TikTok video downloader that downloads source quality videos utilizing TikWM API.
Author-email: Scoofszlo <scoofszlo@gmail.com>
Requires-Python: >=3.11
License-File: LICENSE
Requires-Dist: aiofiles>=24.1.0
Requires-Dist: aiohttp>=3.12.15
Requires-Dist: bs4>=0.0.2
Requires-Dist: pip>=25.1.1
Requires-Dist: platformdirs>=4.3.8
Requires-Dist: playwright>=1.54.0
Requires-Dist: requests>=2.32.4
Requires-Dist: rich>=14.0.0
Requires-Dist: rich-argparse>=1.7.1
Requires-Dist: toml>=0.10.2
Dynamic: license-file
